stcolors/__init__.py
stcolors-0.0.1.dist-info/LICENSE.txt
stcolors-0.0.1.dist-info/METADATA
stcolors-0.0.1.dist-info/WHEEL
stcolors-0.0.1.dist-info/top_level.txt
stcolors-0.0.1.dist-info/RECORD
