Metadata-Version: 2.1
Name: stcolors
Version: 0.0.1
Summary: A RGB Color Library
Home-page: UNKNOWN
Author: St
Author-email: amazingfalcon1@gmail.com
License: MIT
Keywords: rgbcolorsvalue
Platform: UNKNOWN
Classifier: Development Status :: 5 - Production/Stable
Classifier: Intended Audience :: Education
Classifier: Operating System :: Microsoft :: Windows :: Windows 10
Classifier: License :: OSI Approved :: MIT License
Classifier: Programming Language :: Python :: 3
License-File: LICENSE.txt
